<annotation>
	<folder>images</folder>
	<filename>1.png</filename>
	<path>/home/myron/deeplearn/tensorflow/nose/images/1.png</path>
	<source>
		<database>Unknown</database>
	</source>
	<size>
		<width>746</width>
		<height>617</height>
		<depth>3</depth>
	</size>
	<segmented>0</segmented>
	<object>
		<name>nose</name>
		<pose>Unspecified</pose>
		<truncated>0</truncated>
		<difficult>0</difficult>
		<bndbox>
			<xmin>179</xmin>
			<ymin>174</ymin>
			<xmax>601</xmax>
			<ymax>553</ymax>
		</bndbox>
	</object>
</annotation>
